ethpm_types/__init__.py
ethpm_types/abi.py
ethpm_types/ast.py
ethpm_types/base.py
ethpm_types/contract_type.py
ethpm_types/manifest.py
ethpm_types/py.typed
ethpm_types/source.py
ethpm_types/sourcemap.py
ethpm_types/utils.py
ethpm_types/version.py
ethpm_types-0.6.29.dist-info/licenses/LICENSE
ethpm_types-0.6.29.dist-info/METADATA
ethpm_types-0.6.29.dist-info/WHEEL
ethpm_types-0.6.29.dist-info/top_level.txt
ethpm_types-0.6.29.dist-info/RECORD
