Metadata-Version: 2.4
Name: ethpm-types
Version: 0.6.29
Summary: ethpm_types: Implementation of EIP-2678
Home-page: https://github.com/ApeWorX/ethpm-types
Author: ApeWorX Ltd.
Author-email: admin@apeworx.io
License: Apache-2.0
Keywords: ethereum
Classifier: Development Status :: 5 - Production/Stable
Classifier: Intended Audience :: Developers
Classifier: License :: OSI Approved :: Apache Software License
Classifier: Natural Language :: English
Classifier: Operating System :: MacOS
Classifier: Operating System :: POSIX
Classifier: Programming Language :: Python :: 3
Classifier: Programming Language :: Python :: 3.9
Classifier: Programming Language :: Python :: 3.10
Classifier: Programming Language :: Python :: 3.11
Classifier: Programming Language :: Python :: 3.12
Classifier: Programming Language :: Python :: 3.13
Requires-Python: >=3.9,<4
License-File: LICENSE
Requires-Dist: pydantic<3,>=2.9
Requires-Dist: eth-abi<6,>=5.1.0
Requires-Dist: eth-utils<6,>=2.1.0
Requires-Dist: py-cid<0.4,>=0.3.0
Requires-Dist: requests<3,>=2.32.3
Requires-Dist: eth-pydantic-types<0.3,>=0.2.1
Provides-Extra: test
Requires-Dist: pytest>=6.0; extra == "test"
Requires-Dist: pytest-xdist; extra == "test"
Requires-Dist: pytest-cov; extra == "test"
Requires-Dist: hypothesis<7.0,>=6.2.0; extra == "test"
Requires-Dist: PyGithub<2.0,>=1.54; extra == "test"
Requires-Dist: hypothesis-jsonschema==0.19.0; extra == "test"
Requires-Dist: eth-hash[pysha3]; extra == "test"
Provides-Extra: lint
Requires-Dist: ruff>=0.12.0; extra == "lint"
Requires-Dist: mypy<2,>=1.15.0; extra == "lint"
Requires-Dist: types-setuptools; extra == "lint"
Requires-Dist: types-requests; extra == "lint"
Requires-Dist: mdformat>=0.7.22; extra == "lint"
Requires-Dist: mdformat-gfm>=0.3.5; extra == "lint"
Requires-Dist: mdformat-frontmatter>=0.4.1; extra == "lint"
Requires-Dist: mdformat-pyproject>=0.0.2; extra == "lint"
Provides-Extra: doc
Requires-Dist: myst-parser<2,>=1.0.0; extra == "doc"
Requires-Dist: sphinx-click<5,>=4.4.0; extra == "doc"
Requires-Dist: Sphinx<7,>=6.1.3; extra == "doc"
Requires-Dist: sphinx_rtd_theme<2,>=1.2.0; extra == "doc"
Requires-Dist: sphinxcontrib-napoleon>=0.7; extra == "doc"
Provides-Extra: release
Requires-Dist: setuptools>=75.6.0; extra == "release"
Requires-Dist: wheel; extra == "release"
Requires-Dist: twine; extra == "release"
Provides-Extra: dev
Requires-Dist: pytest>=6.0; extra == "dev"
Requires-Dist: pytest-xdist; extra == "dev"
Requires-Dist: pytest-cov; extra == "dev"
Requires-Dist: hypothesis<7.0,>=6.2.0; extra == "dev"
Requires-Dist: PyGithub<2.0,>=1.54; extra == "dev"
Requires-Dist: hypothesis-jsonschema==0.19.0; extra == "dev"
Requires-Dist: eth-hash[pysha3]; extra == "dev"
Requires-Dist: ruff>=0.12.0; extra == "dev"
Requires-Dist: mypy<2,>=1.15.0; extra == "dev"
Requires-Dist: types-setuptools; extra == "dev"
Requires-Dist: types-requests; extra == "dev"
Requires-Dist: mdformat>=0.7.22; extra == "dev"
Requires-Dist: mdformat-gfm>=0.3.5; extra == "dev"
Requires-Dist: mdformat-frontmatter>=0.4.1; extra == "dev"
Requires-Dist: mdformat-pyproject>=0.0.2; extra == "dev"
Requires-Dist: setuptools>=75.6.0; extra == "dev"
Requires-Dist: wheel; extra == "dev"
Requires-Dist: twine; extra == "dev"
Requires-Dist: commitizen<2.41,>=2.40; extra == "dev"
Requires-Dist: pre-commit; extra == "dev"
Requires-Dist: pytest-watch; extra == "dev"
Requires-Dist: IPython; extra == "dev"
Requires-Dist: ipdb; extra == "dev"
Dynamic: author
Dynamic: author-email
Dynamic: classifier
Dynamic: description
Dynamic: description-content-type
Dynamic: home-page
Dynamic: keywords
Dynamic: license
Dynamic: license-file
Dynamic: provides-extra
Dynamic: requires-dist
Dynamic: requires-python
Dynamic: summary
